{
  "version": 1,
  "type": "settings",
  "description": "moobot.348",
  "service": "twitch",
  "settings": [
    {
      "type": "commands_custom",
      "data": [
        {
          "announcement": false,
          "announcement_mods_only": false,
          "announcement_color": "default",
          "counter": 0,
          "counter_usergroups": [4, 3, 2, 1, 0],
          "counter_cooldown": 1,
          "counter_trigger_increment": true,
          "cooldown": 30,
          "expires_disable": false,
          "trigger_states": [5, 4, 3, 2, 1, 0],
          "trigger_usergroups": [4, 3, 2, 1, 0],
          "display_full_duration": false,
          "url_fetch_url": "https://amenard.perso.centrale-marseille.fr/OTPSchedule/aeg.txt",
          "url_fetch_type": "text",
          "url_fetch_version": 1,
          "url_fetch_method": "GET",
          "url_fetch_input_processing": "lowercase",
          "random_number_range_start": 1,
          "random_number_range_end": 100,
          "random_number_range_custom": true,
          "random_number_display_range": false,
          "random_text_1": [],
          "random_text_2": [],
          "random_text_3": [],
          "mod_editable": false,
          "identifier": "aeg",
          "text": "<urlfetch.plain>",
          "enabled": true
        },
        {
          "announcement": false,
          "announcement_mods_only": false,
          "announcement_color": "default",
          "counter": 0,
          "counter_usergroups": [4, 3, 2, 1, 0],
          "counter_cooldown": 1,
          "counter_trigger_increment": true,
          "cooldown": 30,
          "expires_disable": false,
          "trigger_states": [5, 4, 3, 2, 1, 0],
          "trigger_usergroups": [4, 3, 2, 1, 0],
          "display_full_duration": false,
          "url_fetch_url": "https://amenard.perso.centrale-marseille.fr/OTPSchedule/akr.txt",
          "url_fetch_type": "text",
          "url_fetch_version": 1,
          "url_fetch_method": "GET",
          "url_fetch_input_processing": "lowercase",
          "random_number_range_start": 1,
          "random_number_range_end": 100,
          "random_number_range_custom": true,
          "random_number_display_range": false,
          "random_text_1": [],
          "random_text_2": [],
          "random_text_3": [],
          "mod_editable": false,
          "identifier": "akr",
          "text": "<urlfetch.plain>",
          "enabled": true
        },
        {
          "announcement": false,
          "announcement_mods_only": false,
          "announcement_color": "default",
          "counter": 0,
          "counter_usergroups": [4, 3, 2, 1, 0],
          "counter_cooldown": 1,
          "counter_trigger_increment": true,
          "cooldown": 30,
          "expires_disable": false,
          "trigger_states": [5, 4, 3, 2, 1, 0],
          "trigger_usergroups": [4, 3, 2, 1, 0],
          "display_full_duration": false,
          "url_fetch_url": "https://amenard.perso.centrale-marseille.fr/OTPSchedule/bdsa.txt",
          "url_fetch_type": "text",
          "url_fetch_version": 1,
          "url_fetch_method": "GET",
          "url_fetch_input_processing": "lowercase",
          "random_number_range_start": 1,
          "random_number_range_end": 100,
          "random_number_range_custom": true,
          "random_number_display_range": false,
          "random_text_1": [],
          "random_text_2": [],
          "random_text_3": [],
          "mod_editable": false,
          "identifier": "bdsa",
          "text": "<urlfetch.plain>",
          "enabled": true
        },
        {
          "announcement": false,
          "announcement_mods_only": false,
          "announcement_color": "default",
          "counter": 0,
          "counter_usergroups": [4, 3, 2, 1, 0],
          "counter_cooldown": 1,
          "counter_trigger_increment": true,
          "cooldown": 5,
          "expires_disable": false,
          "trigger_states": [5, 4, 3, 2, 1, 0],
          "trigger_usergroups": [4, 3, 2, 1, 0],
          "display_full_duration": false,
          "url_fetch_type": "text",
          "url_fetch_version": 1,
          "url_fetch_method": "GET",
          "random_number_range_start": 1,
          "random_number_range_end": 100,
          "random_number_range_custom": true,
          "random_number_display_range": false,
          "random_text_1": [],
          "random_text_2": [],
          "random_text_3": [],
          "mod_editable": false,
          "identifier": "bestof",
          "text": "Best-of OTP #14 : BATMAN est un caster OTP ?! (TraYtoN nous gêne trop) => https://www.youtube.com/watch?v=B3x_vmnuFt4",
          "enabled": true
        },
        {
          "announcement": false,
          "announcement_mods_only": false,
          "announcement_color": "default",
          "counter": 0,
          "counter_usergroups": [4, 3, 2, 1, 0],
          "counter_cooldown": 1,
          "counter_trigger_increment": true,
          "cooldown": 30,
          "expires_disable": false,
          "trigger_states": [5, 4, 3, 2, 1, 0],
          "trigger_usergroups": [4, 3, 2, 1, 0],
          "display_full_duration": false,
          "url_fetch_url": "https://amenard.perso.centrale-marseille.fr/OTPSchedule/bkr.txt",
          "url_fetch_type": "text",
          "url_fetch_version": 1,
          "url_fetch_method": "GET",
          "url_fetch_input_processing": "lowercase",
          "random_number_range_start": 1,
          "random_number_range_end": 100,
          "random_number_range_custom": true,
          "random_number_display_range": false,
          "random_text_1": [],
          "random_text_2": [],
          "random_text_3": [],
          "mod_editable": false,
          "identifier": "bkr",
          "text": "<urlfetch.plain>",
          "enabled": true
        },
        {
          "announcement": false,
          "announcement_mods_only": false,
          "announcement_color": "default",
          "counter": 0,
          "counter_usergroups": [4, 3, 2, 1, 0],
          "counter_cooldown": 1,
          "counter_trigger_increment": true,
          "cooldown": 5,
          "expires_disable": false,
          "trigger_states": [5, 4, 3, 2, 1, 0],
          "trigger_usergroups": [4, 3, 2, 1, 0],
          "display_full_duration": false,
          "url_fetch_type": "text",
          "url_fetch_version": 1,
          "url_fetch_method": "GET",
          "random_number_range_start": 1,
          "random_number_range_end": 100,
          "random_number_range_custom": true,
          "random_number_display_range": false,
          "random_text_1": [],
          "random_text_2": [],
          "random_text_3": [],
          "mod_editable": false,
          "identifier": "bracket",
          "text": "Vous pouvez retrouver les lobbys ici : https://bit.ly/LOBBYSTFT et le classement là : https://bit.ly/CLASSEMENTCDF",
          "enabled": true
        },
        {
          "announcement": false,
          "announcement_mods_only": false,
          "announcement_color": "default",
          "counter": 0,
          "counter_usergroups": [4, 3, 2, 1, 0],
          "counter_cooldown": 1,
          "counter_trigger_increment": true,
          "cooldown": 5,
          "expires_disable": false,
          "trigger_states": [5, 4, 3, 2, 1, 0],
          "trigger_usergroups": [4, 3, 2, 1, 0],
          "display_full_duration": false,
          "url_fetch_type": "text",
          "url_fetch_version": 1,
          "url_fetch_method": "GET",
          "random_number_range_start": 1,
          "random_number_range_end": 100,
          "random_number_range_custom": true,
          "random_number_display_range": false,
          "random_text_1": [],
          "random_text_2": [],
          "random_text_3": [],
          "mod_editable": false,
          "identifier": "butin",
          "text": "Pour obtenir des capsules de butin, il faut aller sur lolesports et regarder le stream depuis leur site directement en vous connectant avec vos identifiants League of Legends, voici le lien : https://lolesports.com/live/worlds/otplol_",
          "enabled": true
        },
        {
          "announcement": false,
          "announcement_mods_only": false,
          "announcement_color": "default",
          "counter": 0,
          "counter_usergroups": [4, 3, 2, 1, 0],
          "counter_cooldown": 1,
          "counter_trigger_increment": true,
          "cooldown": 5,
          "expires_disable": false,
          "trigger_states": [5, 4, 3, 2, 1, 0],
          "trigger_usergroups": [4, 3, 2, 1, 0],
          "display_full_duration": false,
          "url_fetch_type": "text",
          "url_fetch_version": 1,
          "url_fetch_method": "GET",
          "random_number_range_start": 1,
          "random_number_range_end": 100,
          "random_number_range_custom": true,
          "random_number_display_range": false,
          "random_text_1": [],
          "random_text_2": [],
          "random_text_3": [],
          "mod_editable": true,
          "identifier": "cast",
          "text": "Au cast, nous avons la lumineuse Peaxy et le lumineux Zerotick",
          "enabled": true
        },
        {
          "announcement": false,
          "announcement_mods_only": false,
          "announcement_color": "default",
          "counter": 0,
          "counter_usergroups": [4, 3, 2, 1, 0],
          "counter_cooldown": 1,
          "counter_trigger_increment": true,
          "cooldown": 5,
          "expires_disable": false,
          "trigger_states": [5, 4, 3, 2, 1, 0],
          "trigger_usergroups": [4, 3, 2, 1, 0],
          "display_full_duration": false,
          "url_fetch_type": "text",
          "url_fetch_version": 1,
          "url_fetch_method": "GET",
          "random_number_range_start": 1,
          "random_number_range_end": 100,
          "random_number_range_custom": true,
          "random_number_display_range": false,
          "random_text_1": [],
          "random_text_2": [],
          "random_text_3": [],
          "mod_editable": false,
          "identifier": "cic",
          "text": "La nouvelle carte CIC x KARMINE CORP est arrivée ! Plus d'infos sur : cic.fr/karmine cic.fr/karmine cic.fr/karmine",
          "enabled": true
        },
        {
          "announcement": false,
          "announcement_mods_only": false,
          "announcement_color": "default",
          "counter": 0,
          "counter_usergroups": [4, 3, 2, 1, 0],
          "counter_cooldown": 1,
          "counter_trigger_increment": true,
          "cooldown": 5,
          "expires_disable": false,
          "trigger_states": [5, 4, 3, 2, 1, 0],
          "trigger_usergroups": [4, 3, 2, 1, 0],
          "display_full_duration": false,
          "url_fetch_type": "text",
          "url_fetch_version": 1,
          "url_fetch_method": "GET",
          "random_number_range_start": 1,
          "random_number_range_end": 100,
          "random_number_range_custom": true,
          "random_number_display_range": false,
          "random_text_1": [],
          "random_text_2": [],
          "random_text_3": [],
          "mod_editable": false,
          "identifier": "clip",
          "text": "Afin d'aider le monteur des Best-of OTP, n'hésitez pas à clip un maximum!",
          "enabled": true
        },
        {
          "announcement": false,
          "announcement_mods_only": false,
          "announcement_color": "default",
          "counter": 0,
          "counter_usergroups": [4, 3, 2, 1, 0],
          "counter_cooldown": 1,
          "counter_trigger_increment": true,
          "cooldown": 5,
          "expires_disable": false,
          "trigger_states": [5, 4, 3, 2, 1, 0],
          "trigger_usergroups": [4, 3, 2, 1, 0],
          "display_full_duration": false,
          "url_fetch_type": "text",
          "url_fetch_version": 1,
          "url_fetch_method": "GET",
          "random_number_range_start": 1,
          "random_number_range_end": 100,
          "random_number_range_custom": true,
          "random_number_display_range": false,
          "random_text_1": [],
          "random_text_2": [],
          "random_text_3": [],
          "mod_editable": false,
          "identifier": "croquettes",
          "text": "Les bets sont disponibles en début de draft et jusqu'à environ 1m30 après le début du match ( sauf invade ) . Pour parier vos croquettes, il vous faut regarder au-dessus du chat ( un bandeau violet apparaît ). Vous pouvez aussi cliquer sur vos croquettes pour parier quand le bandeau a disparu !",
          "enabled": true
        },
        {
          "announcement": false,
          "announcement_mods_only": false,
          "announcement_color": "default",
          "counter": 0,
          "counter_usergroups": [4, 3, 2, 1, 0],
          "counter_cooldown": 1,
          "counter_trigger_increment": true,
          "cooldown": 5,
          "expires_disable": false,
          "trigger_states": [5, 4, 3, 2, 1, 0],
          "trigger_usergroups": [4, 3, 2, 1, 0],
          "display_full_duration": false,
          "url_fetch_type": "text",
          "url_fetch_version": 1,
          "url_fetch_method": "GET",
          "random_number_range_start": 1,
          "random_number_range_end": 100,
          "random_number_range_custom": true,
          "random_number_display_range": false,
          "random_text_1": [],
          "random_text_2": [],
          "random_text_3": [],
          "mod_editable": false,
          "identifier": "discord",
          "text": "Le discord officiel OTP LoL est là ! Rejoignez nous ici : https://discord.gg/Qv7vjhevfH . Pour le partenariat discord avec la LFL, écrivez !discordLFL",
          "enabled": true
        },
        {
          "announcement": false,
          "announcement_mods_only": false,
          "announcement_color": "default",
          "counter": 0,
          "counter_usergroups": [4, 3, 2, 1, 0],
          "counter_cooldown": 1,
          "counter_trigger_increment": true,
          "cooldown": 5,
          "expires_disable": false,
          "trigger_states": [5, 4, 3, 2, 1, 0],
          "trigger_usergroups": [4, 3, 2, 1, 0],
          "display_full_duration": false,
          "url_fetch_type": "text",
          "url_fetch_version": 1,
          "url_fetch_method": "GET",
          "random_number_range_start": 1,
          "random_number_range_end": 100,
          "random_number_range_custom": true,
          "random_number_display_range": false,
          "random_text_1": [],
          "random_text_2": [],
          "random_text_3": [],
          "mod_editable": false,
          "identifier": "discordlfl",
          "text": "Rejoignez le Discord officiel de la LFL : https://discord.gg/CNef3Bf7m3",
          "enabled": true
        },
        {
          "announcement": false,
          "announcement_mods_only": false,
          "announcement_color": "default",
          "counter": 0,
          "counter_usergroups": [4, 3, 2, 1, 0],
          "counter_cooldown": 1,
          "counter_trigger_increment": true,
          "cooldown": 5,
          "expires_disable": false,
          "trigger_states": [5, 4, 3, 2, 1, 0],
          "trigger_usergroups": [4, 3, 2, 1, 0],
          "display_full_duration": false,
          "url_fetch_type": "text",
          "url_fetch_version": 1,
          "url_fetch_method": "GET",
          "random_number_range_start": 1,
          "random_number_range_end": 100,
          "random_number_range_custom": true,
          "random_number_display_range": false,
          "random_text_1": [],
          "random_text_2": [],
          "random_text_3": [],
          "mod_editable": false,
          "identifier": "emea",
          "text": "Ce sont les EU Masters (une coupe avec les meilleures équipes de chaque ligue nationale) qui ont été rename en EMEA Masters, car cela inclus des ligues hors europe (Afrique du Nord et Moyen-Orient). M8 passe par un tour de qualification alors que BDSA et KCB sont déjà qualifiés pour le tour principal (grâce à leur place en LFL).",
          "enabled": true
        },
        {
          "announcement": false,
          "announcement_mods_only": false,
          "announcement_color": "default",
          "counter": 0,
          "counter_usergroups": [4, 3, 2, 1, 0],
          "counter_cooldown": 1,
          "counter_trigger_increment": true,
          "cooldown": 30,
          "expires_disable": false,
          "trigger_states": [5, 4, 3, 2, 1, 0],
          "trigger_usergroups": [4, 3, 2, 1, 0],
          "display_full_duration": false,
          "url_fetch_url": "https://amenard.perso.centrale-marseille.fr/OTPSchedule/es.txt",
          "url_fetch_type": "text",
          "url_fetch_version": 1,
          "url_fetch_method": "GET",
          "url_fetch_error": "Pas de match trouvé pour cette équipe (pour le moment)",
          "url_fetch_input_processing": "lowercase",
          "random_number_range_start": 1,
          "random_number_range_end": 100,
          "random_number_range_custom": true,
          "random_number_display_range": false,
          "random_text_1": [],
          "random_text_2": [],
          "random_text_3": [],
          "mod_editable": false,
          "identifier": "es",
          "text": "<urlfetch.plain>",
          "enabled": true
        },
        {
          "announcement": false,
          "announcement_mods_only": false,
          "announcement_color": "default",
          "counter": 0,
          "counter_usergroups": [4, 3, 2, 1, 0],
          "counter_cooldown": 1,
          "counter_trigger_increment": true,
          "cooldown": 5,
          "expires_disable": false,
          "trigger_states": [5, 4, 3, 2, 1, 0],
          "trigger_usergroups": [4, 3, 2, 1, 0],
          "display_full_duration": false,
          "url_fetch_type": "text",
          "url_fetch_version": 1,
          "url_fetch_method": "GET",
          "random_number_range_start": 1,
          "random_number_range_end": 100,
          "random_number_range_custom": true,
          "random_number_display_range": false,
          "random_text_1": [],
          "random_text_2": [],
          "random_text_3": [],
          "mod_editable": false,
          "identifier": "faker",
          "text": "Faker a des douleurs à la main et au bras, il est donc remplacé par Poby. Plus d'infos : https://bit.ly/3CXUiaG",
          "enabled": false
        },
        {
          "announcement": false,
          "announcement_mods_only": false,
          "announcement_color": "default",
          "counter": 0,
          "counter_usergroups": [4, 3, 2, 1, 0],
          "counter_cooldown": 1,
          "counter_trigger_increment": true,
          "cooldown": 5,
          "expires_disable": false,
          "trigger_states": [5, 4, 3, 2, 1, 0],
          "trigger_usergroups": [4, 3, 2, 1, 0],
          "display_full_duration": false,
          "url_fetch_type": "text",
          "url_fetch_version": 1,
          "url_fetch_method": "GET",
          "random_number_range_start": 1,
          "random_number_range_end": 100,
          "random_number_range_custom": true,
          "random_number_display_range": false,
          "random_text_1": [],
          "random_text_2": [],
          "random_text_3": [],
          "mod_editable": false,
          "identifier": "fenêtré",
          "text": "Les joueurs coréens jouent en fenêtré pour plusieurs raisons : garder la même taille pour la fenêtre du jeu peu importe l'écran (pc bang, locaux de leur team, chez eux, sur scène), prendre plus facilement l'information sur la carte, ne pas avoir à faire des grands mouvements de souris...",
          "enabled": false
        },
        {
          "announcement": false,
          "announcement_mods_only": false,
          "announcement_color": "default",
          "counter": 0,
          "counter_usergroups": [4, 3, 2, 1, 0],
          "counter_cooldown": 1,
          "counter_trigger_increment": true,
          "cooldown": 5,
          "expires_disable": false,
          "trigger_states": [5, 4, 3, 2, 1, 0],
          "trigger_usergroups": [4, 3, 2, 1, 0],
          "display_full_duration": false,
          "url_fetch_type": "text",
          "url_fetch_version": 1,
          "url_fetch_method": "GET",
          "random_number_range_start": 1,
          "random_number_range_end": 100,
          "random_number_range_custom": true,
          "random_number_display_range": false,
          "random_text_1": [],
          "random_text_2": [],
          "random_text_3": [],
          "mod_editable": false,
          "identifier": "gl",
          "text": "Constitue ton équipe avec des mates de ton école, et rejoins La Grosse Ligue LoL 👊 : https://universityesports.fr/game/league-of-legends",
          "enabled": false
        },
        {
          "announcement": false,
          "announcement_mods_only": false,
          "announcement_color": "default",
          "counter": 0,
          "counter_usergroups": [4, 3, 2, 1, 0],
          "counter_cooldown": 1,
          "counter_trigger_increment": true,
          "cooldown": 30,
          "expires_disable": false,
          "trigger_states": [5, 4, 3, 2, 1, 0],
          "trigger_usergroups": [4, 3, 2, 1, 0],
          "display_full_duration": false,
          "url_fetch_url": "https://amenard.perso.centrale-marseille.fr/OTPSchedule/go.txt",
          "url_fetch_type": "text",
          "url_fetch_version": 1,
          "url_fetch_method": "GET",
          "url_fetch_input_processing": "lowercase",
          "random_number_range_start": 1,
          "random_number_range_end": 100,
          "random_number_range_custom": true,
          "random_number_display_range": false,
          "random_text_1": [],
          "random_text_2": [],
          "random_text_3": [],
          "mod_editable": false,
          "identifier": "go",
          "text": "<urlfetch.plain>",
          "enabled": true
        },
        {
          "announcement": false,
          "announcement_mods_only": false,
          "announcement_color": "default",
          "counter": 0,
          "counter_usergroups": [4, 3, 2, 1, 0],
          "counter_cooldown": 1,
          "counter_trigger_increment": true,
          "cooldown": 5,
          "expires_disable": false,
          "trigger_states": [5, 4, 3, 2, 1, 0],
          "trigger_usergroups": [4, 3, 2, 1, 0],
          "display_full_duration": false,
          "url_fetch_type": "text",
          "url_fetch_version": 1,
          "url_fetch_method": "GET",
          "random_number_range_start": 1,
          "random_number_range_end": 100,
          "random_number_range_custom": true,
          "random_number_display_range": false,
          "random_text_1": [],
          "random_text_2": [],
          "random_text_3": [],
          "mod_editable": false,
          "identifier": "guest",
          "text": "L'invité du jour est Eika! Il sera là entre chaque game! https://twitter.com/Eikalol",
          "enabled": false
        },
        {
          "announcement": false,
          "announcement_mods_only": false,
          "announcement_color": "default",
          "counter": 0,
          "counter_usergroups": [4, 3, 2, 1, 0],
          "counter_cooldown": 1,
          "counter_trigger_increment": true,
          "cooldown": 30,
          "expires_disable": false,
          "trigger_states": [5, 4, 3, 2, 1, 0],
          "trigger_usergroups": [4, 3, 2, 1, 0],
          "display_full_duration": false,
          "url_fetch_url": "https://amenard.perso.centrale-marseille.fr/OTPSchedule/gw.txt",
          "url_fetch_type": "text",
          "url_fetch_version": 1,
          "url_fetch_method": "GET",
          "random_number_range_start": 1,
          "random_number_range_end": 100,
          "random_number_range_custom": true,
          "random_number_display_range": false,
          "random_text_1": [],
          "random_text_2": [],
          "random_text_3": [],
          "mod_editable": false,
          "identifier": "gw",
          "text": "<urlfetch.plain>",
          "enabled": true
        },
        {
          "announcement": false,
          "announcement_mods_only": false,
          "announcement_color": "default",
          "counter": 0,
          "counter_usergroups": [4, 3, 2, 1, 0],
          "counter_cooldown": 1,
          "counter_trigger_increment": true,
          "cooldown": 30,
          "expires_disable": false,
          "trigger_states": [5, 4, 3, 2, 1, 0],
          "trigger_usergroups": [4, 3, 2, 1, 0],
          "display_full_duration": false,
          "url_fetch_url": "https://amenard.perso.centrale-marseille.fr/OTPSchedule/ijc.txt",
          "url_fetch_type": "text",
          "url_fetch_version": 1,
          "url_fetch_method": "GET",
          "url_fetch_input_processing": "lowercase",
          "random_number_range_start": 1,
          "random_number_range_end": 100,
          "random_number_range_custom": true,
          "random_number_display_range": false,
          "random_text_1": [],
          "random_text_2": [],
          "random_text_3": [],
          "mod_editable": false,
          "identifier": "ijc",
          "text": "<urlfetch.plain>",
          "enabled": true
        },
        {
          "announcement": false,
          "announcement_mods_only": false,
          "announcement_color": "default",
          "counter": 0,
          "counter_usergroups": [4, 3, 2, 1, 0],
          "counter_cooldown": 1,
          "counter_trigger_increment": true,
          "cooldown": 5,
          "expires_disable": false,
          "trigger_states": [5, 4, 3, 2, 1, 0],
          "trigger_usergroups": [4, 3, 2, 1, 0],
          "display_full_duration": false,
          "url_fetch_type": "text",
          "url_fetch_version": 1,
          "url_fetch_method": "GET",
          "random_number_range_start": 1,
          "random_number_range_end": 100,
          "random_number_range_custom": true,
          "random_number_display_range": false,
          "random_text_1": [],
          "random_text_2": [],
          "random_text_3": [],
          "mod_editable": false,
          "identifier": "intro",
          "text": "Retrouvez la musique officielle de la LFL : My Time to Shine de Damned Anthem, Southside Dren sur https://open.spotify.com/track/21byk9pNgBLBJ1BLU7Rxpt?si=cafe8574b2674f92&nd=1 Tous droits réservés par Position Music",
          "enabled": false
        },
        {
          "announcement": false,
          "announcement_mods_only": false,
          "announcement_color": "default",
          "counter": 0,
          "counter_usergroups": [4, 3, 2, 1, 0],
          "counter_cooldown": 1,
          "counter_trigger_increment": true,
          "cooldown": 30,
          "expires_disable": false,
          "trigger_states": [5, 4, 3, 2, 1, 0],
          "trigger_usergroups": [4, 3, 2, 1, 0],
          "display_full_duration": false,
          "url_fetch_url": "https://amenard.perso.centrale-marseille.fr/OTPSchedule/izi.txt",
          "url_fetch_type": "text",
          "url_fetch_version": 1,
          "url_fetch_method": "GET",
          "url_fetch_input_processing": "lowercase",
          "random_number_range_start": 1,
          "random_number_range_end": 100,
          "random_number_range_custom": true,
          "random_number_display_range": false,
          "random_text_1": [],
          "random_text_2": [],
          "random_text_3": [],
          "mod_editable": false,
          "identifier": "izi",
          "text": "<urlfetch.plain>",
          "enabled": true
        },
        {
          "announcement": false,
          "announcement_mods_only": false,
          "announcement_color": "default",
          "counter": 0,
          "counter_usergroups": [4, 3, 2, 1, 0],
          "counter_cooldown": 1,
          "counter_trigger_increment": true,
          "cooldown": 30,
          "expires_disable": false,
          "trigger_states": [5, 4, 3, 2, 1, 0],
          "trigger_usergroups": [4, 3, 2, 1, 0],
          "display_full_duration": false,
          "url_fetch_url": "https://amenard.perso.centrale-marseille.fr/OTPSchedule/jl.txt",
          "url_fetch_type": "text",
          "url_fetch_version": 1,
          "url_fetch_method": "GET",
          "random_number_range_start": 1,
          "random_number_range_end": 100,
          "random_number_range_custom": true,
          "random_number_display_range": false,
          "random_text_1": [],
          "random_text_2": [],
          "random_text_3": [],
          "mod_editable": false,
          "identifier": "jl",
          "text": "<urlfetch.plain>",
          "enabled": true
        },
        {
          "announcement": false,
          "announcement_mods_only": false,
          "announcement_color": "default",
          "counter": 0,
          "counter_usergroups": [4, 3, 2, 1, 0],
          "counter_cooldown": 1,
          "counter_trigger_increment": true,
          "cooldown": 30,
          "expires_disable": false,
          "trigger_states": [5, 4, 3, 2, 1, 0],
          "trigger_usergroups": [4, 3, 2, 1, 0],
          "display_full_duration": false,
          "url_fetch_url": "https://amenard.perso.centrale-marseille.fr/OTPSchedule/kcb.txt",
          "url_fetch_type": "text",
          "url_fetch_version": 1,
          "url_fetch_method": "GET",
          "url_fetch_input_processing": "lowercase",
          "random_number_range_start": 1,
          "random_number_range_end": 100,
          "random_number_range_custom": true,
          "random_number_display_range": false,
          "random_text_1": [],
          "random_text_2": [],
          "random_text_3": [],
          "mod_editable": false,
          "identifier": "kcb",
          "text": "<urlfetch.plain>",
          "enabled": true
        },
        {
          "announcement": false,
          "announcement_mods_only": false,
          "announcement_color": "default",
          "counter": 0,
          "counter_usergroups": [4, 3, 2, 1, 0],
          "counter_cooldown": 1,
          "counter_trigger_increment": true,
          "cooldown": 30,
          "expires_disable": false,
          "trigger_states": [5, 4, 3, 2, 1, 0],
          "trigger_usergroups": [4, 3, 2, 1, 0],
          "display_full_duration": false,
          "url_fetch_url": "https://amenard.perso.centrale-marseille.fr/OTPSchedule/ke.txt",
          "url_fetch_type": "text",
          "url_fetch_version": 1,
          "url_fetch_method": "GET",
          "url_fetch_input_processing": "lowercase",
          "random_number_range_start": 1,
          "random_number_range_end": 100,
          "random_number_range_custom": true,
          "random_number_display_range": false,
          "random_text_1": [],
          "random_text_2": [],
          "random_text_3": [],
          "mod_editable": false,
          "identifier": "ke",
          "text": "<urlfetch.plain>",
          "enabled": true
        },
        {
          "announcement": false,
          "announcement_mods_only": false,
          "announcement_color": "default",
          "counter": 0,
          "counter_usergroups": [4, 3, 2, 1, 0],
          "counter_cooldown": 1,
          "counter_trigger_increment": true,
          "cooldown": 30,
          "expires_disable": false,
          "trigger_states": [5, 4, 3, 2, 1, 0],
          "trigger_usergroups": [4, 3, 2, 1, 0],
          "display_full_duration": false,
          "url_fetch_type": "text",
          "url_fetch_version": 1,
          "url_fetch_method": "GET",
          "random_number_range_start": 1,
          "random_number_range_end": 100,
          "random_number_range_custom": true,
          "random_number_display_range": false,
          "random_text_1": [],
          "random_text_2": [],
          "random_text_3": [],
          "mod_editable": false,
          "identifier": "kia",
          "text": "Avec OTP et Kia suivez la voie des légendes. RDV sur https://bit.ly/VersLaL%C3%A9gende pour en savoir plus",
          "enabled": true
        },
        {
          "announcement": false,
          "announcement_mods_only": false,
          "announcement_color": "default",
          "counter": 0,
          "counter_usergroups": [4, 3, 2, 1, 0],
          "counter_cooldown": 1,
          "counter_trigger_increment": true,
          "cooldown": 5,
          "expires_disable": false,
          "trigger_states": [5, 4, 3, 2, 1, 0],
          "trigger_usergroups": [4, 3, 2, 1, 0],
          "display_full_duration": false,
          "url_fetch_type": "text",
          "url_fetch_version": 1,
          "url_fetch_method": "GET",
          "random_number_range_start": 1,
          "random_number_range_end": 100,
          "random_number_range_custom": true,
          "random_number_display_range": false,
          "random_text_1": [],
          "random_text_2": [],
          "random_text_3": [],
          "mod_editable": false,
          "identifier": "lck",
          "text": "La LCK jouera les matchs de cette semaine en OFFLINE puis seront diffusés à partir de 12h de mercredi à vendredi et 10h samedi et dimanche.",
          "enabled": false
        },
        {
          "announcement": false,
          "announcement_mods_only": false,
          "announcement_color": "default",
          "counter": 0,
          "counter_usergroups": [4, 3, 2, 1, 0],
          "counter_cooldown": 1,
          "counter_trigger_increment": true,
          "cooldown": 5,
          "expires_disable": false,
          "trigger_states": [5, 4, 3, 2, 1, 0],
          "trigger_usergroups": [4, 3, 2, 1, 0],
          "display_full_duration": false,
          "url_fetch_type": "text",
          "url_fetch_version": 1,
          "url_fetch_method": "GET",
          "random_number_range_start": 1,
          "random_number_range_end": 100,
          "random_number_range_custom": true,
          "random_number_display_range": false,
          "random_text_1": [],
          "random_text_2": [],
          "random_text_3": [],
          "mod_editable": false,
          "identifier": "lcs",
          "text": "Pour l'instant les LCS ne sont pas diffusables sur otp, mais on essaie pour le futur! https://clips.twitch.tv/DrabResoluteJalapenoLeeroyJenkins-Z-aRAB2oWA_VGw9e",
          "enabled": true
        },
        {
          "announcement": false,
          "announcement_mods_only": false,
          "announcement_color": "default",
          "counter": 0,
          "counter_usergroups": [4, 3, 2, 1, 0],
          "counter_cooldown": 1,
          "counter_trigger_increment": true,
          "cooldown": 5,
          "expires_disable": false,
          "trigger_states": [5, 4, 3, 2, 1, 0],
          "trigger_usergroups": [4, 3, 2, 1, 0],
          "display_full_duration": false,
          "url_fetch_type": "text",
          "url_fetch_version": 1,
          "url_fetch_method": "GET",
          "random_number_range_start": 1,
          "random_number_range_end": 100,
          "random_number_range_custom": true,
          "random_number_display_range": false,
          "random_text_1": [],
          "random_text_2": [],
          "random_text_3": [],
          "mod_editable": false,
          "identifier": "lec",
          "text": "Suite à la pause annuelle côté riot, le LEC est en pause et reprendra le 15 juillet à 18h (17h30 preshow) pour plus d'informations : https://lol.fandom.com/wiki/LEC/2022_Season/Summer_Season",
          "enabled": false
        },
        {
          "announcement": false,
          "announcement_mods_only": false,
          "announcement_color": "default",
          "counter": 0,
          "counter_usergroups": [4, 3, 2, 1, 0],
          "counter_cooldown": 1,
          "counter_trigger_increment": true,
          "cooldown": 5,
          "expires_disable": false,
          "trigger_states": [5, 4, 3, 2, 1, 0],
          "trigger_usergroups": [4, 3, 2, 1, 0],
          "display_full_duration": false,
          "url_fetch_type": "text",
          "url_fetch_version": 1,
          "url_fetch_method": "GET",
          "random_number_range_start": 1,
          "random_number_range_end": 100,
          "random_number_range_custom": true,
          "random_number_display_range": false,
          "random_text_1": [],
          "random_text_2": [],
          "random_text_3": [],
          "mod_editable": false,
          "identifier": "lfl",
          "text": "La LFL c'est tous les Mercredi & Jeudi dès 17h30! Si vous souhaitez voir les précédents résultats rendez-vous sur : https://lollfl.com/",
          "enabled": false
        },
        {
          "announcement": false,
          "announcement_mods_only": false,
          "announcement_color": "default",
          "counter": 0,
          "counter_usergroups": [4, 3, 2, 1, 0],
          "counter_cooldown": 1,
          "counter_trigger_increment": true,
          "cooldown": 30,
          "expires_disable": false,
          "trigger_states": [5, 4, 3, 2, 1, 0],
          "trigger_usergroups": [4, 3, 2, 1, 0],
          "display_full_duration": false,
          "url_fetch_url": "https://amenard.perso.centrale-marseille.fr/OTPSchedule/lil.txt",
          "url_fetch_type": "text",
          "url_fetch_version": 1,
          "url_fetch_method": "GET",
          "url_fetch_error": "Pas de match trouvé pour cette équipe (pour le moment)",
          "url_fetch_input_processing": "lowercase",
          "random_number_range_start": 1,
          "random_number_range_end": 100,
          "random_number_range_custom": true,
          "random_number_display_range": false,
          "random_text_1": [],
          "random_text_2": [],
          "random_text_3": [],
          "mod_editable": false,
          "identifier": "lil",
          "text": "<urlfetch.plain>",
          "enabled": true
        },
        {
          "announcement": false,
          "announcement_mods_only": false,
          "announcement_color": "default",
          "counter": 0,
          "counter_usergroups": [4, 3, 2, 1, 0],
          "counter_cooldown": 1,
          "counter_trigger_increment": true,
          "cooldown": 120,
          "expires_disable": false,
          "trigger_states": [5, 4, 3, 2, 1, 0],
          "trigger_usergroups": [4, 3, 2, 1, 0],
          "display_full_duration": false,
          "url_fetch_type": "text",
          "url_fetch_version": 1,
          "url_fetch_method": "GET",
          "random_number_range_start": 1,
          "random_number_range_end": 100,
          "random_number_range_custom": true,
          "random_number_display_range": false,
          "random_text_1": [],
          "random_text_2": [],
          "random_text_3": [],
          "mod_editable": false,
          "identifier": "lunettes",
          "text": "Trayton porte des lunettes de soleil / une casquette, car il souffre régulièrement de migraines ophtalmiques",
          "enabled": true
        },
        {
          "announcement": false,
          "announcement_mods_only": false,
          "announcement_color": "default",
          "counter": 0,
          "counter_usergroups": [4, 3, 2, 1, 0],
          "counter_cooldown": 1,
          "counter_trigger_increment": true,
          "cooldown": 30,
          "expires_disable": false,
          "trigger_states": [5, 4, 3, 2, 1, 0],
          "trigger_usergroups": [4, 3, 2, 1, 0],
          "display_full_duration": false,
          "url_fetch_url": "https://amenard.perso.centrale-marseille.fr/OTPSchedule/m8.txt",
          "url_fetch_type": "text",
          "url_fetch_version": 1,
          "url_fetch_method": "GET",
          "random_number_range_start": 1,
          "random_number_range_end": 100,
          "random_number_range_custom": true,
          "random_number_display_range": false,
          "random_text_1": [],
          "random_text_2": [],
          "random_text_3": [],
          "mod_editable": false,
          "identifier": "m8",
          "text": "<urlfetch.plain>",
          "enabled": true
        },
        {
          "announcement": false,
          "announcement_mods_only": false,
          "announcement_color": "default",
          "counter": 0,
          "counter_usergroups": [4, 3, 2, 1, 0],
          "counter_cooldown": 1,
          "counter_trigger_increment": true,
          "cooldown": 5,
          "expires_disable": false,
          "trigger_states": [5, 4, 3, 2, 1, 0],
          "trigger_usergroups": [4, 3, 2, 1, 0],
          "display_full_duration": false,
          "url_fetch_url": "https://amenard.perso.centrale-marseille.fr/OTPSchedule/<args.1>.txt",
          "url_fetch_type": "text",
          "url_fetch_version": 1,
          "url_fetch_method": "GET",
          "url_fetch_error": "Pas de match trouvé pour cette équipe (pour le moment...)",
          "url_fetch_input_processing": "lowercase",
          "random_number_range_start": 1,
          "random_number_range_end": 100,
          "random_number_range_custom": true,
          "random_number_display_range": false,
          "random_text_1": [],
          "random_text_2": [],
          "random_text_3": [],
          "mod_editable": false,
          "identifier": "match",
          "text": "<urlfetch.plain>",
          "enabled": true
        },
        {
          "announcement": false,
          "announcement_mods_only": false,
          "announcement_color": "default",
          "counter": 0,
          "counter_usergroups": [4, 3, 2, 1, 0],
          "counter_cooldown": 1,
          "counter_trigger_increment": true,
          "cooldown": 5,
          "expires_disable": false,
          "trigger_states": [5, 4, 3, 2, 1, 0],
          "trigger_usergroups": [4, 3, 2, 1, 0],
          "display_full_duration": false,
          "url_fetch_type": "text",
          "url_fetch_version": 1,
          "url_fetch_method": "GET",
          "random_number_range_start": 1,
          "random_number_range_end": 100,
          "random_number_range_custom": true,
          "random_number_display_range": false,
          "random_text_1": [],
          "random_text_2": [],
          "random_text_3": [],
          "mod_editable": false,
          "identifier": "merch",
          "text": "La nouvelle collection du merch est disponible sur https://shop.otp.tv/?utm_source=moobot&utm_medium=twitch !",
          "enabled": true
        },
        {
          "announcement": false,
          "announcement_mods_only": false,
          "announcement_color": "default",
          "counter": 0,
          "counter_usergroups": [4, 3, 2, 1, 0],
          "counter_cooldown": 1,
          "counter_trigger_increment": true,
          "cooldown": 5,
          "expires_disable": false,
          "trigger_states": [5, 4, 3, 2, 1, 0],
          "trigger_usergroups": [4, 3, 2, 1, 0],
          "display_full_duration": false,
          "url_fetch_type": "text",
          "url_fetch_version": 1,
          "url_fetch_method": "GET",
          "random_number_range_start": 1,
          "random_number_range_end": 100,
          "random_number_range_custom": true,
          "random_number_display_range": false,
          "random_text_1": [],
          "random_text_2": [],
          "random_text_3": [],
          "mod_editable": false,
          "identifier": "merci",
          "text": "Merci pour le(s) sub(s) !",
          "enabled": true
        },
        {
          "announcement": false,
          "announcement_mods_only": false,
          "announcement_color": "default",
          "counter": 0,
          "counter_usergroups": [4, 3, 2, 1, 0],
          "counter_cooldown": 1,
          "counter_trigger_increment": true,
          "cooldown": 30,
          "expires_disable": false,
          "trigger_states": [5, 4, 3, 2, 1, 0],
          "trigger_usergroups": [4, 3, 2, 1, 0],
          "display_full_duration": false,
          "url_fetch_url": "https://amenard.perso.centrale-marseille.fr/OTPSchedule/mhsc.txt",
          "url_fetch_type": "text",
          "url_fetch_version": 1,
          "url_fetch_method": "GET",
          "url_fetch_input_processing": "lowercase",
          "random_number_range_start": 1,
          "random_number_range_end": 100,
          "random_number_range_custom": true,
          "random_number_display_range": false,
          "random_text_1": [],
          "random_text_2": [],
          "random_text_3": [],
          "mod_editable": false,
          "identifier": "mhsc",
          "text": "<urlfetch.plain>",
          "enabled": true
        },
        {
          "announcement": false,
          "announcement_mods_only": false,
          "announcement_color": "default",
          "counter": 0,
          "counter_usergroups": [4, 3, 2, 1, 0],
          "counter_cooldown": 1,
          "counter_trigger_increment": true,
          "cooldown": 5,
          "expires_disable": false,
          "trigger_states": [5, 4, 3, 2, 1, 0],
          "trigger_usergroups": [4, 3, 2, 1, 0],
          "display_full_duration": false,
          "url_fetch_type": "text",
          "url_fetch_version": 1,
          "url_fetch_method": "GET",
          "random_number_range_start": 1,
          "random_number_range_end": 100,
          "random_number_range_custom": true,
          "random_number_display_range": false,
          "random_text_1": [],
          "random_text_2": [],
          "random_text_3": [],
          "mod_editable": false,
          "identifier": "modo",
          "text": "La modération OTP recrute pour le MSI ! (donc matin / début d'aprem) Si vous êtes intéressé.es pour modérer, n'hésitez pas à postuler ici ! https://forms.gle/gSeRC5dCmFMvUsi58",
          "enabled": false
        },
        {
          "announcement": false,
          "announcement_mods_only": false,
          "announcement_color": "default",
          "counter": 0,
          "counter_usergroups": [4, 3, 2, 1, 0],
          "counter_cooldown": 1,
          "counter_trigger_increment": true,
          "cooldown": 5,
          "expires_disable": false,
          "trigger_states": [5, 4, 3, 2, 1, 0],
          "trigger_usergroups": [4, 3, 2, 1, 0],
          "display_full_duration": false,
          "url_fetch_type": "text",
          "url_fetch_version": 1,
          "url_fetch_method": "GET",
          "random_number_range_start": 1,
          "random_number_range_end": 100,
          "random_number_range_custom": true,
          "random_number_display_range": false,
          "random_text_1": [],
          "random_text_2": [],
          "random_text_3": [],
          "mod_editable": false,
          "identifier": "mvp",
          "text": "Vous pouvez aller voter pour le mvp de la game en réponse au dernier post twitter le concernant : https://twitter.com/LFLOfficiel",
          "enabled": true
        },
        {
          "announcement": false,
          "announcement_mods_only": false,
          "announcement_color": "default",
          "counter": 0,
          "counter_usergroups": [4, 3, 2, 1, 0],
          "counter_cooldown": 1,
          "counter_trigger_increment": true,
          "cooldown": 5,
          "expires_disable": false,
          "trigger_states": [5, 4, 3, 2, 1, 0],
          "trigger_usergroups": [4, 3, 2, 1, 0],
          "display_full_duration": false,
          "url_fetch_type": "text",
          "url_fetch_version": 1,
          "url_fetch_method": "GET",
          "random_number_range_start": 1,
          "random_number_range_end": 100,
          "random_number_range_custom": true,
          "random_number_display_range": false,
          "random_text_1": [],
          "random_text_2": [],
          "random_text_3": [],
          "mod_editable": false,
          "identifier": "nice",
          "text": "La billetterie des LFL Days Nice est ouverte ! Venez vivre l'expérience LFL en live avec toutes les équipes https://urlz.fr/pkjD",
          "enabled": false
        },
        {
          "announcement": false,
          "announcement_mods_only": false,
          "announcement_color": "default",
          "counter": 0,
          "counter_usergroups": [4, 3, 2, 1, 0],
          "counter_cooldown": 1,
          "counter_trigger_increment": true,
          "cooldown": 5,
          "expires_disable": false,
          "trigger_states": [5, 4, 3, 2, 1, 0],
          "trigger_usergroups": [4, 3, 2, 1, 0],
          "display_full_duration": false,
          "url_fetch_type": "text",
          "url_fetch_version": 1,
          "url_fetch_method": "GET",
          "random_number_range_start": 1,
          "random_number_range_end": 100,
          "random_number_range_custom": true,
          "random_number_display_range": false,
          "random_text_1": [],
          "random_text_2": [],
          "random_text_3": [],
          "mod_editable": false,
          "identifier": "omen|hyperx",
          "text": "Profitez de 20% de remise sur les gammes OMEN, VICTUS et HYPERX sur la boutique HP avec le code 20DIV2 : https://www.hp.com/fr-fr/shop/offer.aspx?p=c-lol-div2",
          "enabled": true
        },
        {
          "announcement": false,
          "announcement_mods_only": false,
          "announcement_color": "default",
          "counter": 0,
          "counter_usergroups": [4, 3, 2, 1, 0],
          "counter_cooldown": 1,
          "counter_trigger_increment": true,
          "cooldown": 5,
          "expires_disable": false,
          "trigger_states": [5, 4, 3, 2, 1, 0],
          "trigger_usergroups": [4, 3, 2, 1, 0],
          "display_full_duration": false,
          "url_fetch_type": "text",
          "url_fetch_version": 1,
          "url_fetch_method": "GET",
          "random_number_range_start": 1,
          "random_number_range_end": 100,
          "random_number_range_custom": true,
          "random_number_display_range": false,
          "random_text_1": [],
          "random_text_2": [],
          "random_text_3": [],
          "mod_editable": false,
          "identifier": "outro",
          "text": "La musique d'outro lfl est \"karnage vice\" dispo sur spotify",
          "enabled": true
        },
        {
          "announcement": false,
          "announcement_mods_only": false,
          "announcement_color": "default",
          "counter": 0,
          "counter_usergroups": [4, 3, 2, 1, 0],
          "counter_cooldown": 1,
          "counter_trigger_increment": true,
          "cooldown": 5,
          "expires_disable": false,
          "trigger_states": [5, 4, 3, 2, 1, 0],
          "trigger_usergroups": [4, 3, 2, 1, 0],
          "display_full_duration": false,
          "url_fetch_type": "text",
          "url_fetch_version": 1,
          "url_fetch_method": "GET",
          "random_number_range_start": 1,
          "random_number_range_end": 100,
          "random_number_range_custom": true,
          "random_number_display_range": false,
          "random_text_1": [],
          "random_text_2": [],
          "random_text_3": [],
          "mod_editable": false,
          "identifier": "patch",
          "text": "LFL, Div2 : 14.10",
          "enabled": true
        },
        {
          "announcement": false,
          "announcement_mods_only": false,
          "announcement_color": "default",
          "counter": 0,
          "counter_usergroups": [4, 3, 2, 1, 0],
          "counter_cooldown": 1,
          "counter_trigger_increment": true,
          "cooldown": 30,
          "expires_disable": false,
          "trigger_states": [5, 4, 3, 2, 1, 0],
          "trigger_usergroups": [4, 3, 2, 1, 0],
          "display_full_duration": false,
          "url_fetch_url": "https://amenard.perso.centrale-marseille.fr/OTPSchedule/pcs.txt",
          "url_fetch_type": "text",
          "url_fetch_version": 1,
          "url_fetch_method": "GET",
          "url_fetch_error": "Pas de match trouvé pour cette équipe (pour le moment)",
          "url_fetch_input_processing": "lowercase",
          "random_number_range_start": 1,
          "random_number_range_end": 100,
          "random_number_range_custom": true,
          "random_number_display_range": false,
          "random_text_1": [],
          "random_text_2": [],
          "random_text_3": [],
          "mod_editable": false,
          "identifier": "pcs",
          "text": "<urlfetch.plain>",
          "enabled": true
        },
        {
          "announcement": false,
          "announcement_mods_only": false,
          "announcement_color": "default",
          "counter": 0,
          "counter_usergroups": [4, 3, 2, 1, 0],
          "counter_cooldown": 1,
          "counter_trigger_increment": true,
          "cooldown": 5,
          "expires_disable": false,
          "trigger_states": [5, 4, 3, 2, 1, 0],
          "trigger_usergroups": [4, 3, 2, 1, 0],
          "display_full_duration": false,
          "url_fetch_type": "text",
          "url_fetch_version": 1,
          "url_fetch_method": "GET",
          "random_number_range_start": 1,
          "random_number_range_end": 100,
          "random_number_range_custom": true,
          "random_number_display_range": false,
          "random_text_1": [],
          "random_text_2": [],
          "random_text_3": [],
          "mod_editable": false,
          "identifier": "pemea",
          "text": "Pour retrouver les musiques utilisées pendant les EMEA Masters c'est ici : https://bit.ly/3NLSrdg",
          "enabled": true
        },
        {
          "announcement": false,
          "announcement_mods_only": false,
          "announcement_color": "default",
          "counter": 0,
          "counter_usergroups": [4, 3, 2, 1, 0],
          "counter_cooldown": 1,
          "counter_trigger_increment": true,
          "cooldown": 5,
          "expires_disable": false,
          "trigger_states": [5, 4, 3, 2, 1, 0],
          "trigger_usergroups": [4, 3, 2, 1, 0],
          "display_full_duration": false,
          "url_fetch_type": "text",
          "url_fetch_version": 1,
          "url_fetch_method": "GET",
          "random_number_range_start": 1,
          "random_number_range_end": 100,
          "random_number_range_custom": true,
          "random_number_display_range": false,
          "random_text_1": [],
          "random_text_2": [],
          "random_text_3": [],
          "mod_editable": false,
          "identifier": "planning",
          "text": "Le planning de la semaine est disponible en dessous du stream sur PC ou en appuyant sur le logo otplol_ si vous êtes sur téléphone, allez ensuite dans l'onglet \"à propos\". Il est mis à jour chaque début de semaine.",
          "enabled": true
        },
        {
          "announcement": false,
          "announcement_mods_only": false,
          "announcement_color": "default",
          "counter": 0,
          "counter_usergroups": [4, 3, 2, 1, 0],
          "counter_cooldown": 1,
          "counter_trigger_increment": true,
          "cooldown": 5,
          "expires_disable": false,
          "trigger_states": [5, 4, 3, 2, 1, 0],
          "trigger_usergroups": [4, 3, 2, 1, 0],
          "display_full_duration": false,
          "url_fetch_type": "text",
          "url_fetch_version": 1,
          "url_fetch_method": "GET",
          "random_number_range_start": 1,
          "random_number_range_end": 100,
          "random_number_range_custom": true,
          "random_number_display_range": false,
          "random_text_1": [],
          "random_text_2": [],
          "random_text_3": [],
          "mod_editable": false,
          "identifier": "playlist",
          "text": "Pour voir les musiques utilisées, utilisez les commandes suivantes (selon la ligue): !plec , !plfl , !plck, !pemea !pmsi.",
          "enabled": true
        },
        {
          "announcement": false,
          "announcement_mods_only": false,
          "announcement_color": "default",
          "counter": 0,
          "counter_usergroups": [4, 3, 2, 1, 0],
          "counter_cooldown": 1,
          "counter_trigger_increment": true,
          "cooldown": 5,
          "expires_disable": false,
          "trigger_states": [5, 4, 3, 2, 1, 0],
          "trigger_usergroups": [4, 3, 2, 1, 0],
          "display_full_duration": false,
          "url_fetch_type": "text",
          "url_fetch_version": 1,
          "url_fetch_method": "GET",
          "random_number_range_start": 1,
          "random_number_range_end": 100,
          "random_number_range_custom": true,
          "random_number_display_range": false,
          "random_text_1": [],
          "random_text_2": [],
          "random_text_3": [],
          "mod_editable": false,
          "identifier": "plck",
          "text": "Les musiques utilisées pendant les pauses de LCK sont en grande partie des musiques Riot (login screen, musique de worlds, etc...) , tirés de la playlist Gratuite de Riot sur Spotify https://open.spotify.com/playlist/5hDYD44imzFZEqTfAoco1N",
          "enabled": true
        },
        {
          "announcement": false,
          "announcement_mods_only": false,
          "announcement_color": "default",
          "counter": 0,
          "counter_usergroups": [4, 3, 2, 1, 0],
          "counter_cooldown": 1,
          "counter_trigger_increment": true,
          "cooldown": 5,
          "expires_disable": false,
          "trigger_states": [5, 4, 3, 2, 1, 0],
          "trigger_usergroups": [4, 3, 2, 1, 0],
          "display_full_duration": false,
          "url_fetch_type": "text",
          "url_fetch_version": 1,
          "url_fetch_method": "GET",
          "random_number_range_start": 1,
          "random_number_range_end": 100,
          "random_number_range_custom": true,
          "random_number_display_range": false,
          "random_text_1": [],
          "random_text_2": [],
          "random_text_3": [],
          "mod_editable": false,
          "identifier": "plec",
          "text": "Voilà la playlist des musiques utilisées pendant le LEC https://twitter.com/LEC/status/1360536956774584322?s=19",
          "enabled": true
        },
        {
          "announcement": false,
          "announcement_mods_only": false,
          "announcement_color": "default",
          "counter": 0,
          "counter_usergroups": [4, 3, 2, 1, 0],
          "counter_cooldown": 1,
          "counter_trigger_increment": true,
          "cooldown": 5,
          "expires_disable": false,
          "trigger_states": [5, 4, 3, 2, 1, 0],
          "trigger_usergroups": [4, 3, 2, 1, 0],
          "display_full_duration": false,
          "url_fetch_type": "text",
          "url_fetch_version": 1,
          "url_fetch_method": "GET",
          "random_number_range_start": 1,
          "random_number_range_end": 100,
          "random_number_range_custom": true,
          "random_number_display_range": false,
          "random_text_1": [],
          "random_text_2": [],
          "random_text_3": [],
          "mod_editable": false,
          "identifier": "plfl",
          "text": "La playlist sera dispo dans quelques jours ! PRANKEX",
          "enabled": true
        },
        {
          "announcement": false,
          "announcement_mods_only": false,
          "announcement_color": "default",
          "counter": 0,
          "counter_usergroups": [4, 3, 2, 1, 0],
          "counter_cooldown": 1,
          "counter_trigger_increment": true,
          "cooldown": 5,
          "expires_disable": false,
          "trigger_states": [5, 4, 3, 2, 1, 0],
          "trigger_usergroups": [4, 3, 2, 1, 0],
          "display_full_duration": false,
          "url_fetch_type": "text",
          "url_fetch_version": 1,
          "url_fetch_method": "GET",
          "random_number_range_start": 1,
          "random_number_range_end": 100,
          "random_number_range_custom": true,
          "random_number_display_range": false,
          "random_text_1": [],
          "random_text_2": [],
          "random_text_3": [],
          "mod_editable": false,
          "identifier": "pmsi",
          "text": "Les musiques du MSI n'ont pas été publiées par Riot pour le moment, nous n'avons donc pas de playlist à vous donner.",
          "enabled": true
        },
        {
          "announcement": false,
          "announcement_mods_only": false,
          "announcement_color": "default",
          "counter": 0,
          "counter_usergroups": [4, 3, 2, 1, 0],
          "counter_cooldown": 1,
          "counter_trigger_increment": true,
          "cooldown": 5,
          "expires_disable": false,
          "trigger_states": [5, 4, 3, 2, 1, 0],
          "trigger_usergroups": [4, 3, 2, 1, 0],
          "display_full_duration": false,
          "url_fetch_type": "text",
          "url_fetch_version": 1,
          "url_fetch_method": "GET",
          "random_number_range_start": 1,
          "random_number_range_end": 100,
          "random_number_range_custom": true,
          "random_number_display_range": false,
          "random_text_1": [],
          "random_text_2": [],
          "random_text_3": [],
          "mod_editable": false,
          "identifier": "pworlds",
          "text": "Vous pouvez retrouver les musiques des worlds ici => PRANKEX",
          "enabled": true
        },
        {
          "announcement": false,
          "announcement_mods_only": false,
          "announcement_color": "default",
          "counter": 0,
          "counter_usergroups": [4, 3, 2, 1, 0],
          "counter_cooldown": 1,
          "counter_trigger_increment": true,
          "cooldown": 5,
          "expires_disable": false,
          "trigger_states": [5, 4, 3, 2, 1, 0],
          "trigger_usergroups": [4, 3, 2, 1, 0],
          "display_full_duration": false,
          "url_fetch_type": "text",
          "url_fetch_version": 1,
          "url_fetch_method": "GET",
          "random_number_range_start": 1,
          "random_number_range_end": 100,
          "random_number_range_custom": true,
          "random_number_display_range": false,
          "random_text_1": [],
          "random_text_2": [],
          "random_text_3": [],
          "mod_editable": false,
          "identifier": "rediff",
          "text": "Pendant la rediff, les spoils sont INTERDITS, que ce soit une demande ou une réponse. Merci de ne pas spoil au risque de sanction. C'est pour cette raison que la plupart des rediffs sont en Subonly. Si vous voulez un résultat, demandez le en MP ou cherchez sur https://lol.fandom.com (Il n'y a pas de bet en rediff)",
          "enabled": true
        },
        {
          "announcement": false,
          "announcement_mods_only": false,
          "announcement_color": "default",
          "counter": 0,
          "counter_usergroups": [4, 3, 2, 1, 0],
          "counter_cooldown": 1,
          "counter_trigger_increment": true,
          "cooldown": 5,
          "expires_disable": false,
          "trigger_states": [5, 4, 3, 2, 1, 0],
          "trigger_usergroups": [4, 3, 2, 1, 0],
          "display_full_duration": false,
          "url_fetch_type": "text",
          "url_fetch_version": 1,
          "url_fetch_method": "GET",
          "random_number_range_start": 1,
          "random_number_range_end": 100,
          "random_number_range_custom": true,
          "random_number_display_range": false,
          "random_text_1": [],
          "random_text_2": [],
          "random_text_3": [],
          "mod_editable": false,
          "identifier": "resultats",
          "text": "Vous pouvez suivre les résultats du MSI ici => https://lol.fandom.com/wiki/2024_Mid-Season_Invitational",
          "enabled": false
        },
        {
          "announcement": false,
          "announcement_mods_only": false,
          "announcement_color": "default",
          "counter": 0,
          "counter_usergroups": [4, 3, 2, 1, 0],
          "counter_cooldown": 1,
          "counter_trigger_increment": true,
          "cooldown": 5,
          "expires_disable": false,
          "trigger_states": [5, 4, 3, 2, 1, 0],
          "trigger_usergroups": [4, 3, 2, 1, 0],
          "display_full_duration": false,
          "url_fetch_type": "text",
          "url_fetch_version": 1,
          "url_fetch_method": "GET",
          "random_number_range_start": 1,
          "random_number_range_end": 100,
          "random_number_range_custom": true,
          "random_number_display_range": false,
          "random_text_1": [],
          "random_text_2": [],
          "random_text_3": [],
          "mod_editable": false,
          "identifier": "règles",
          "text": "Règles du 1v1 : BO3 | Faire 2 kills | Prendre la tour | Kill pendant la mort subite ( zone qui se referme sur les joueurs après 7min de jeu ).",
          "enabled": false
        },
        {
          "announcement": false,
          "announcement_mods_only": false,
          "announcement_color": "default",
          "counter": 0,
          "counter_usergroups": [4, 3, 2, 1, 0],
          "counter_cooldown": 1,
          "counter_trigger_increment": true,
          "cooldown": 5,
          "expires_disable": false,
          "trigger_states": [5, 4, 3, 2, 1, 0],
          "trigger_usergroups": [4, 3, 2, 1, 0],
          "display_full_duration": false,
          "url_fetch_type": "text",
          "url_fetch_version": 1,
          "url_fetch_method": "GET",
          "random_number_range_start": 1,
          "random_number_range_end": 100,
          "random_number_range_custom": true,
          "random_number_display_range": false,
          "random_text_1": [],
          "random_text_2": [],
          "random_text_3": [],
          "mod_editable": false,
          "identifier": "site",
          "text": "Voici le lien vers notre site OTP, le site est encore en bêta :D : https://www.otp.tv/",
          "enabled": true
        },
        {
          "announcement": false,
          "announcement_mods_only": false,
          "announcement_color": "default",
          "counter": 0,
          "counter_usergroups": [4, 3, 2, 1, 0],
          "counter_cooldown": 1,
          "counter_trigger_increment": true,
          "cooldown": 30,
          "expires_disable": false,
          "trigger_states": [5, 4, 3, 2, 1, 0],
          "trigger_usergroups": [4, 3, 2, 1, 0],
          "display_full_duration": false,
          "url_fetch_url": "https://amenard.perso.centrale-marseille.fr/OTPSchedule/sly.txt",
          "url_fetch_type": "text",
          "url_fetch_version": 1,
          "url_fetch_method": "GET",
          "random_number_range_start": 1,
          "random_number_range_end": 100,
          "random_number_range_custom": true,
          "random_number_display_range": false,
          "random_text_1": [],
          "random_text_2": [],
          "random_text_3": [],
          "mod_editable": false,
          "identifier": "sly",
          "text": "<urlfetch.plain>",
          "enabled": true
        },
        {
          "announcement": false,
          "announcement_mods_only": false,
          "announcement_color": "default",
          "counter": 0,
          "counter_usergroups": [4, 3, 2, 1, 0],
          "counter_cooldown": 1,
          "counter_trigger_increment": true,
          "cooldown": 30,
          "expires_disable": false,
          "trigger_states": [5, 4, 3, 2, 1, 0],
          "trigger_usergroups": [4, 3, 2, 1, 0],
          "display_full_duration": false,
          "url_fetch_url": "https://amenard.perso.centrale-marseille.fr/OTPSchedule/tds.txt",
          "url_fetch_type": "text",
          "url_fetch_version": 1,
          "url_fetch_method": "GET",
          "url_fetch_error": "Pas de match trouvé pour cette équipe (pour le moment)",
          "url_fetch_input_processing": "lowercase",
          "random_number_range_start": 1,
          "random_number_range_end": 100,
          "random_number_range_custom": true,
          "random_number_display_range": false,
          "random_text_1": [],
          "random_text_2": [],
          "random_text_3": [],
          "mod_editable": false,
          "identifier": "tds",
          "text": "<urlfetch.plain>",
          "enabled": true
        },
        {
          "announcement": false,
          "announcement_mods_only": false,
          "announcement_color": "default",
          "counter": 0,
          "counter_usergroups": [4, 3, 2, 1, 0],
          "counter_cooldown": 1,
          "counter_trigger_increment": true,
          "cooldown": 5,
          "expires_disable": false,
          "trigger_states": [5, 4, 3, 2, 1, 0],
          "trigger_usergroups": [4, 3, 2, 1, 0],
          "display_full_duration": false,
          "url_fetch_type": "text",
          "url_fetch_version": 1,
          "url_fetch_method": "GET",
          "random_number_range_start": 1,
          "random_number_range_end": 100,
          "random_number_range_custom": true,
          "random_number_display_range": false,
          "random_text_1": [],
          "random_text_2": [],
          "random_text_3": [],
          "mod_editable": false,
          "identifier": "teamslfl",
          "text": "Pour voir le planning de chaque team LFL dans la semaine qui arrive, écrivez simplement ! suivi de l'acronyme de la team ( !bds !go !gw !kc !ldlc !me !msf !sly !opl !vit)",
          "enabled": false
        },
        {
          "announcement": false,
          "announcement_mods_only": false,
          "announcement_color": "default",
          "counter": 0,
          "counter_usergroups": [4, 3, 2, 1, 0],
          "counter_cooldown": 1,
          "counter_trigger_increment": true,
          "cooldown": 5,
          "expires_disable": false,
          "trigger_states": [5, 4, 3, 2, 1, 0],
          "trigger_usergroups": [4, 3, 2, 1, 0],
          "display_full_duration": false,
          "url_fetch_type": "text",
          "url_fetch_version": 1,
          "url_fetch_method": "GET",
          "random_number_range_start": 1,
          "random_number_range_end": 100,
          "random_number_range_custom": true,
          "random_number_display_range": false,
          "random_text_1": [],
          "random_text_2": [],
          "random_text_3": [],
          "mod_editable": false,
          "identifier": "tft",
          "text": "Aujourd'hui OTP cast la finale de la Coupe de France de TFT à partir de 10h. Vous pouvez suivre la LCK sur la chaîne officielle (en anglais).",
          "enabled": false
        },
        {
          "announcement": false,
          "announcement_mods_only": false,
          "announcement_color": "default",
          "counter": 0,
          "counter_usergroups": [4, 3, 2, 1, 0],
          "counter_cooldown": 1,
          "counter_trigger_increment": true,
          "cooldown": 5,
          "expires_disable": false,
          "trigger_states": [5, 4, 3, 2, 1, 0],
          "trigger_usergroups": [4, 3, 2, 1, 0],
          "display_full_duration": false,
          "url_fetch_type": "text",
          "url_fetch_version": 1,
          "url_fetch_method": "GET",
          "random_number_range_start": 1,
          "random_number_range_end": 100,
          "random_number_range_custom": true,
          "random_number_display_range": false,
          "random_text_1": [],
          "random_text_2": [],
          "random_text_3": [],
          "mod_editable": false,
          "identifier": "twittermodé",
          "text": "Si vous avez des questions vous pouvez mp un modo ou mp le twitter de la modération : https://twitter.com/ModerationOtp",
          "enabled": true
        },
        {
          "announcement": false,
          "announcement_mods_only": false,
          "announcement_color": "default",
          "counter": 0,
          "counter_usergroups": [4, 3, 2, 1, 0],
          "counter_cooldown": 1,
          "counter_trigger_increment": true,
          "cooldown": 5,
          "expires_disable": false,
          "trigger_states": [5, 4, 3, 2, 1, 0],
          "trigger_usergroups": [4, 3, 2, 1, 0],
          "display_full_duration": false,
          "url_fetch_type": "text",
          "url_fetch_version": 1,
          "url_fetch_method": "GET",
          "random_number_range_start": 1,
          "random_number_range_end": 100,
          "random_number_range_custom": true,
          "random_number_display_range": false,
          "random_text_1": [],
          "random_text_2": [],
          "random_text_3": [],
          "mod_editable": false,
          "identifier": "up&down",
          "text": "Les Up&Down sont des matchs entre les 2 derniers de la LFL et les 2 premiers de div 2 (en 2022, les 2 splits cumulés dans les 2 cas). Mirage Elyandra a conservé sa place en LFL, et IZI retourne en Div 2. Le vainqueur de ce dernier BO5 monte en LFL et le perdant descend en Div 2.",
          "enabled": false
        },
        {
          "announcement": false,
          "announcement_mods_only": false,
          "announcement_color": "default",
          "counter": 0,
          "counter_usergroups": [4, 3, 2, 1, 0],
          "counter_cooldown": 1,
          "counter_trigger_increment": true,
          "cooldown": 5,
          "expires_disable": false,
          "trigger_states": [5, 4, 3, 2, 1, 0],
          "trigger_usergroups": [4, 3, 2, 1, 0],
          "display_full_duration": false,
          "url_fetch_type": "text",
          "url_fetch_version": 1,
          "url_fetch_method": "GET",
          "random_number_range_start": 1,
          "random_number_range_end": 100,
          "random_number_range_custom": true,
          "random_number_display_range": false,
          "random_text_1": [],
          "random_text_2": [],
          "random_text_3": [],
          "mod_editable": false,
          "identifier": "vit",
          "enabled": false
        },
        {
          "announcement": false,
          "announcement_mods_only": false,
          "announcement_color": "default",
          "counter": 0,
          "counter_usergroups": [4, 3, 2, 1, 0],
          "counter_cooldown": 1,
          "counter_trigger_increment": true,
          "cooldown": 30,
          "expires_disable": false,
          "trigger_states": [5, 4, 3, 2, 1, 0],
          "trigger_usergroups": [4, 3, 2, 1, 0],
          "display_full_duration": false,
          "url_fetch_url": "https://amenard.perso.centrale-marseille.fr/OTPSchedule/vitb.txt",
          "url_fetch_type": "text",
          "url_fetch_version": 1,
          "url_fetch_method": "GET",
          "url_fetch_input_processing": "lowercase",
          "random_number_range_start": 1,
          "random_number_range_end": 100,
          "random_number_range_custom": true,
          "random_number_display_range": false,
          "random_text_1": [],
          "random_text_2": [],
          "random_text_3": [],
          "mod_editable": false,
          "identifier": "vitb",
          "text": "<urlfetch.plain>",
          "enabled": true
        },
        {
          "announcement": false,
          "announcement_mods_only": false,
          "announcement_color": "default",
          "counter": 0,
          "counter_usergroups": [4, 3, 2, 1, 0],
          "counter_cooldown": 1,
          "counter_trigger_increment": true,
          "cooldown": 5,
          "expires_disable": false,
          "trigger_states": [5, 4, 3, 2, 1, 0],
          "trigger_usergroups": [4, 3, 2, 1, 0],
          "display_full_duration": false,
          "url_fetch_type": "text",
          "url_fetch_version": 1,
          "url_fetch_method": "GET",
          "youtube_username": "UCfl5hER45ci1_WtLs1NeBnQ",
          "random_number_range_start": 1,
          "random_number_range_end": 100,
          "random_number_range_custom": true,
          "random_number_display_range": false,
          "random_text_1": [],
          "random_text_2": [],
          "random_text_3": [],
          "mod_editable": false,
          "identifier": "vlog",
          "text": "VLOG OTP | Les finales du MSI vécues par le crew OTP c'est par ici => https://bit.ly/FINALESMSI",
          "enabled": true
        },
        {
          "announcement": false,
          "announcement_mods_only": false,
          "announcement_color": "default",
          "counter": 0,
          "counter_usergroups": [4, 3, 2, 1, 0],
          "counter_cooldown": 1,
          "counter_trigger_increment": true,
          "cooldown": 5,
          "expires_disable": false,
          "trigger_states": [5, 4, 3, 2, 1, 0],
          "trigger_usergroups": [4, 3, 2, 1, 0],
          "chat_text": "si vous vous ennuyez ^^",
          "display_full_duration": false,
          "url_fetch_type": "text",
          "url_fetch_version": 1,
          "url_fetch_method": "GET",
          "random_number_range_start": 1,
          "random_number_range_end": 100,
          "random_number_range_custom": true,
          "random_number_display_range": false,
          "random_text_1": [],
          "random_text_2": [],
          "random_text_3": [],
          "mod_editable": false,
          "identifier": "youtube",
          "text": "La chaine replay: https://www.youtube.com/c/OTPLoL | La chaine vidéos https://www.youtube.com/channel/UCfl5hER45ci1_WtLs1NeBnQ",
          "enabled": true
        },
        {
          "announcement": false,
          "announcement_mods_only": false,
          "announcement_color": "default",
          "counter": 0,
          "counter_usergroups": [4, 3, 2, 1, 0],
          "counter_cooldown": 1,
          "counter_trigger_increment": true,
          "cooldown": 30,
          "expires_disable": false,
          "trigger_states": [5, 4, 3, 2, 1, 0],
          "trigger_usergroups": [4, 3, 2, 1, 0],
          "display_full_duration": false,
          "url_fetch_url": "https://amenard.perso.centrale-marseille.fr/OTPSchedule/zer.txt",
          "url_fetch_type": "text",
          "url_fetch_version": 1,
          "url_fetch_method": "GET",
          "url_fetch_error": "Pas de match trouvé pour cette équipe (pour le moment)",
          "url_fetch_input_processing": "lowercase",
          "random_number_range_start": 1,
          "random_number_range_end": 100,
          "random_number_range_custom": true,
          "random_number_display_range": false,
          "random_text_1": [],
          "random_text_2": [],
          "random_text_3": [],
          "mod_editable": false,
          "identifier": "zer",
          "text": "<urlfetch.plain>",
          "enabled": true
        }
      ]
    }
  ]
}
